sanic_app/__init__.py
sanic_app/apps.py
sanic_app/camera.py
sanic_app/conftest.py
sanic_app/delivered_key.py
sanic_app/sanic_class.py
sanic_app/sdk_functions.py
sanic_app/test_client.py
sdk_sw_sanic-0.0.3.dist-info/METADATA
sdk_sw_sanic-0.0.3.dist-info/WHEEL
sdk_sw_sanic-0.0.3.dist-info/top_level.txt
sdk_sw_sanic-0.0.3.dist-info/RECORD
