Metadata-Version: 2.1
Name: sdk-sw-sanic
Version: 0.0.3
Summary: SDK sanic application
Author: swalih
Author-email: <swalihchungath@gmail.com>
Keywords: python,video,stream,video stream,camera stream,palm
Classifier: Development Status :: 1 - Planning
Classifier: Intended Audience :: Developers
Classifier: Programming Language :: Python :: 3
Classifier: Operating System :: Unix
Classifier: Operating System :: MacOS :: MacOS X
Classifier: Operating System :: Microsoft :: Windows
Requires-Dist: opencv-python
Requires-Dist: sanic
Requires-Dist: cryptography
Requires-Dist: numpy
Requires-Dist: pytest
